{"devicePlatform":"","logFolder":"C:\\Users\\angel\\git\\testgeneral\\Reports\\SuiteLogin\\20171026_104023","runData":{"hostName":"angel - W10-PRJ","os":"Windows 10 64bit","katalonVersion":"4.8.0.2","browser":"Firefox 56.0","hostAddress":"192.168.110.241","sessionId":"b1d90eb5-fd32-437d-91e3-b1f96b57bedf","seleniumVersion":"2.53.0","proxyInformation":"ProxyInformation{proxyOption\u003dNO_PROXY, proxyServerType\u003dHTTP, password\u003d, proxyServerAddress\u003d, proxyServerPort\u003d0}","platform":"Windows 10"},"type":"TEST_SUITE","name":"SuiteLogin","id":"Test Suites/SuiteLogin","source":"","message":"Test Cases/Crear User","description":"","startTime":1509007227917,"endTime":1509007292024,"childRecords":[{"isOptional":false,"type":"TEST_CASE","name":"Test Cases/Crear User","id":"Test Cases/Crear User","source":"C:\\\\Users\\\\angel\\\\git\\\\testgeneralTest Cases\\\\Crear User.tc","message":"Test Cases/Crear User","description":"","startTime":1509007228914,"endTime":1509007291948,"childRecords":[{"testStatus":{"stackTrace":"","statusValue":"INFO"},"type":"MESSAGE","name":"","message":"Evaluating variables for test case","startTime":1509007229826,"endTime":0,"childRecords":[],"interuppted":false},{"index":1,"isIgnoredIfFailed":false,"type":"TEST_STEP","name":"openBrowser","message":"Browser is opened with url: \u0027http://1106.logicommerce.net/?forceView\u003d1\u0027","description":"","startTime":1509007232311,"endTime":1509007257757,"childRecords":[{"testStatus":{"stackTrace":"","statusValue":"PASSED"},"type":"MESSAGE","name":"","message":"Browser is opened with url: \u0027http://1106.logicommerce.net/?forceView\u003d1\u0027","startTime":1509007257733,"endTime":0,"childRecords":[],"interuppted":false}],"interuppted":false},{"index":2,"isIgnoredIfFailed":false,"type":"TEST_STEP","name":"Statement - SignIn \u003d new com.kms.katalon.core.testobject.TestObject(SignIn)","description":"Creamos un nuevo TestObject para el boton Create Account\\r\\n","startTime":1509007257759,"endTime":1509007257794,"childRecords":[],"interuppted":false},{"index":3,"isIgnoredIfFailed":false,"type":"TEST_STEP","name":"Statement - SignIn.addProperty(\"xpath\", EQUALS, \"//a[contains(@href,\u0027/user\u0027)][@title\u003d\u0027Sign In\u0027]\", true)","description":"Decimos que este testobject contiene la propiedad Xpath que nos interesa","startTime":1509007257795,"endTime":1509007257831,"childRecords":[],"interuppted":false},{"index":4,"isIgnoredIfFailed":false,"type":"TEST_STEP","name":"click","message":"Object: \u0027SignIn\u0027 is clicked on","description":"clickamos en el test Obect\\r\\n","startTime":1509007257833,"endTime":1509007258939,"childRecords":[{"testStatus":{"stackTrace":"","statusValue":"PASSED"},"type":"MESSAGE","name":"","message":"Object: \u0027SignIn\u0027 is clicked on","startTime":1509007258939,"endTime":0,"childRecords":[],"interuppted":false}],"interuppted":false},{"index":5,"isIgnoredIfFailed":false,"type":"TEST_STEP","name":"Statement - CreateAccount \u003d new com.kms.katalon.core.testobject.TestObject(CreateAccount)","description":"Creamos un nuevo TestObject para el boton Create Account\\r\\n","startTime":1509007258939,"endTime":1509007258948,"childRecords":[],"interuppted":false},{"index":6,"isIgnoredIfFailed":false,"type":"TEST_STEP","name":"Statement - CreateAccount.addProperty(\"xpath\", EQUALS, \"//a[contains(@href,\u0027/createAccount\u0027)][@class\u003d\u0027btn\u0027]\", true)","description":"Decimos que este testobject contiene la propiedad Xpath que nos interesa","startTime":1509007258955,"endTime":1509007258958,"childRecords":[],"interuppted":false},{"index":7,"isIgnoredIfFailed":false,"type":"TEST_STEP","name":"click","message":"Object: \u0027CreateAccount\u0027 is clicked on","description":"clickamos en el test Obect\\r\\n","startTime":1509007258959,"endTime":1509007266636,"childRecords":[{"testStatus":{"stackTrace":"","statusValue":"PASSED"},"type":"MESSAGE","name":"","message":"Object: \u0027CreateAccount\u0027 is clicked on","startTime":1509007266632,"endTime":0,"childRecords":[],"interuppted":false}],"interuppted":false},{"index":8,"isIgnoredIfFailed":false,"type":"TEST_STEP","name":"Statement - s \u003d \"tlg-\"","description":"","startTime":1509007266636,"endTime":1509007266636,"childRecords":[],"interuppted":false},{"index":9,"isIgnoredIfFailed":false,"type":"TEST_STEP","name":"Statement - s +\u003d new java.util.Date().format(\"yyyyMMdd\")","description":"","startTime":1509007266636,"endTime":1509007266670,"childRecords":[],"interuppted":false},{"index":10,"isIgnoredIfFailed":false,"type":"TEST_STEP","name":"Statement - s +\u003d \"-\"","description":"","startTime":1509007266671,"endTime":1509007266671,"childRecords":[],"interuppted":false},{"index":11,"isIgnoredIfFailed":false,"type":"TEST_STEP","name":"Statement - randomGenerator \u003d new java.util.Random()","description":"","startTime":1509007266671,"endTime":1509007266681,"childRecords":[],"interuppted":false},{"index":12,"isIgnoredIfFailed":false,"type":"TEST_STEP","name":"Statement - hash \u003d randomGenerator.nextInt(100)","description":"","startTime":1509007266687,"endTime":1509007266690,"childRecords":[],"interuppted":false},{"index":13,"isIgnoredIfFailed":false,"type":"TEST_STEP","name":"Statement - s +\u003d hash","description":"","startTime":1509007266691,"endTime":1509007266692,"childRecords":[],"interuppted":false},{"index":14,"isIgnoredIfFailed":false,"type":"TEST_STEP","name":"Statement - s \u003d s + \"@tlg.com\"","description":"Hasta aqui generamos una cadena de formato tlg-fecha-hash@tlg.com\\r\\n","startTime":1509007266695,"endTime":1509007266700,"childRecords":[],"interuppted":false},{"index":15,"isIgnoredIfFailed":false,"type":"TEST_STEP","name":"Statement - mailGlobal \u003d s","description":"","startTime":1509007266701,"endTime":1509007266714,"childRecords":[],"interuppted":false},{"index":16,"isIgnoredIfFailed":false,"type":"TEST_STEP","name":"Statement - mail \u003d new com.kms.katalon.core.testobject.TestObject(mail)","description":"Creamos un nuevo TestObject para el campo Email\\r\\n","startTime":1509007266720,"endTime":1509007266739,"childRecords":[],"interuppted":false},{"index":17,"isIgnoredIfFailed":false,"type":"TEST_STEP","name":"Statement - mail.addProperty(\"xpath\", EQUALS, \"//input[@id\u003d\u0027userEmailField\u0027]\", true)","description":"Decimos que este testobject contiene la propiedad Xpath que nos interesa","startTime":1509007266761,"endTime":1509007266764,"childRecords":[],"interuppted":false},{"index":18,"isIgnoredIfFailed":false,"type":"TEST_STEP","name":"setText","message":"Text \u0027tlg-20171026-50@tlg.com\u0027 is set on object \u0027mail\u0027","description":"rellenamos  el test Obect\\r\\n","startTime":1509007266765,"endTime":1509007273882,"childRecords":[{"testStatus":{"stackTrace":"","statusValue":"PASSED"},"type":"MESSAGE","name":"","message":"Text \u0027tlg-20171026-50@tlg.com\u0027 is set on object \u0027mail\u0027","startTime":1509007273879,"endTime":0,"childRecords":[],"interuppted":false}],"interuppted":false},{"index":19,"isIgnoredIfFailed":false,"type":"TEST_STEP","name":"Statement - Adreca1 \u003d new com.kms.katalon.core.testobject.TestObject(Adreca1)","description":"Creamos un nuevo TestObject para el campo Adreca test 1\\r\\n","startTime":1509007273882,"endTime":1509007273889,"childRecords":[],"interuppted":false},{"index":20,"isIgnoredIfFailed":false,"type":"TEST_STEP","name":"Statement - Adreca1.addProperty(\"xpath\", EQUALS, \"//input[@id\u003d\u0027userAddress1Field\u0027]\", true)","description":"Decimos que este testobject contiene la propiedad Xpath que nos interesa","startTime":1509007273892,"endTime":1509007273895,"childRecords":[],"interuppted":false},{"index":21,"isIgnoredIfFailed":false,"type":"TEST_STEP","name":"setText","message":"Text \u0027Adreca test 1\u0027 is set on object \u0027Adreca1\u0027","description":"rellenamos  el test Obect\\r\\n","startTime":1509007273895,"endTime":1509007274714,"childRecords":[{"testStatus":{"stackTrace":"","statusValue":"PASSED"},"type":"MESSAGE","name":"","message":"Text \u0027Adreca test 1\u0027 is set on object \u0027Adreca1\u0027","startTime":1509007274712,"endTime":0,"childRecords":[],"interuppted":false}],"interuppted":false},{"index":22,"isIgnoredIfFailed":false,"type":"TEST_STEP","name":"Statement - Adreca2 \u003d new com.kms.katalon.core.testobject.TestObject(Adreca2)","description":"Creamos un nuevo TestObject para el campo Adreca test 2\\r\\n","startTime":1509007274714,"endTime":1509007274714,"childRecords":[],"interuppted":false},{"index":23,"isIgnoredIfFailed":false,"type":"TEST_STEP","name":"Statement - Adreca2.addProperty(\"xpath\", EQUALS, \"//input[@id\u003d\u0027userAddress2Field\u0027]\", true)","description":"Decimos que este testobject contiene la propiedad Xpath que nos interesa","startTime":1509007274714,"endTime":1509007274728,"childRecords":[],"interuppted":false},{"index":24,"isIgnoredIfFailed":false,"type":"TEST_STEP","name":"setText","message":"Text \u0027Adreca test 2\u0027 is set on object \u0027Adreca2\u0027","description":"rellenamos  el test Obect\\r\\n","startTime":1509007274730,"endTime":1509007275503,"childRecords":[{"testStatus":{"stackTrace":"","statusValue":"PASSED"},"type":"MESSAGE","name":"","message":"Text \u0027Adreca test 2\u0027 is set on object \u0027Adreca2\u0027","startTime":1509007275500,"endTime":0,"childRecords":[],"interuppted":false}],"interuppted":false},{"index":25,"isIgnoredIfFailed":false,"type":"TEST_STEP","name":"Statement - Compania \u003d new com.kms.katalon.core.testobject.TestObject(Compania)","description":"Creamos un nuevo TestObject para el campo Compania\\r\\n","startTime":1509007275503,"endTime":1509007275505,"childRecords":[],"interuppted":false},{"index":26,"isIgnoredIfFailed":false,"type":"TEST_STEP","name":"Statement - Compania.addProperty(\"xpath\", EQUALS, \"//input[@id\u003d\u0027userCompanyField\u0027]\", true)","description":"Decimos que este testobject contiene la propiedad Xpath que nos interesa","startTime":1509007275505,"endTime":1509007275507,"childRecords":[],"interuppted":false},{"index":27,"isIgnoredIfFailed":false,"type":"TEST_STEP","name":"setText","message":"Text \u0027 Compania Test\u0027 is set on object \u0027Compania\u0027","description":"rellenamos  el test Obect\\r\\n","startTime":1509007275507,"endTime":1509007276259,"childRecords":[{"testStatus":{"stackTrace":"","statusValue":"PASSED"},"type":"MESSAGE","name":"","message":"Text \u0027 Compania Test\u0027 is set on object \u0027Compania\u0027","startTime":1509007276257,"endTime":0,"childRecords":[],"interuppted":false}],"interuppted":false},{"index":28,"isIgnoredIfFailed":false,"type":"TEST_STEP","name":"Statement - Name \u003d new com.kms.katalon.core.testobject.TestObject(Name)","description":"Creamos un nuevo TestObject para el campo Name\\r\\n","startTime":1509007276260,"endTime":1509007276262,"childRecords":[],"interuppted":false},{"index":29,"isIgnoredIfFailed":false,"type":"TEST_STEP","name":"Statement - Name.addProperty(\"xpath\", EQUALS, \"//input[@id\u003d\u0027userFirstNameField\u0027]\", true)","description":"Decimos que este testobject contiene la propiedad Xpath que nos interesa","startTime":1509007276263,"endTime":1509007276270,"childRecords":[],"interuppted":false},{"index":30,"isIgnoredIfFailed":false,"type":"TEST_STEP","name":"setText","message":"Text \u0027 Nombre Test\u0027 is set on object \u0027Name\u0027","description":"rellenamos  el test Obect\\r\\n","startTime":1509007276270,"endTime":1509007276979,"childRecords":[{"testStatus":{"stackTrace":"","statusValue":"PASSED"},"type":"MESSAGE","name":"","message":"Text \u0027 Nombre Test\u0027 is set on object \u0027Name\u0027","startTime":1509007276977,"endTime":0,"childRecords":[],"interuppted":false}],"interuppted":false},{"index":31,"isIgnoredIfFailed":false,"type":"TEST_STEP","name":"Statement - Apellido \u003d new com.kms.katalon.core.testobject.TestObject(Apellido)","description":"Creamos un nuevo TestObject para el campo Apellido\\r\\n","startTime":1509007276979,"endTime":1509007276980,"childRecords":[],"interuppted":false},{"index":32,"isIgnoredIfFailed":false,"type":"TEST_STEP","name":"Statement - Apellido.addProperty(\"xpath\", EQUALS, \"//input[@id\u003d\u0027userLastNameField\u0027]\", true)","description":"Decimos que este testobject contiene la propiedad Xpath que nos interesa","startTime":1509007276980,"endTime":1509007276980,"childRecords":[],"interuppted":false},{"index":33,"isIgnoredIfFailed":false,"type":"TEST_STEP","name":"setText","message":"Text \u0027 Apellido Test\u0027 is set on object \u0027Apellido\u0027","description":"rellenamos  el test Obect\\r\\n","startTime":1509007276980,"endTime":1509007277692,"childRecords":[{"testStatus":{"stackTrace":"","statusValue":"PASSED"},"type":"MESSAGE","name":"","message":"Text \u0027 Apellido Test\u0027 is set on object \u0027Apellido\u0027","startTime":1509007277691,"endTime":0,"childRecords":[],"interuppted":false}],"interuppted":false},{"index":34,"isIgnoredIfFailed":false,"type":"TEST_STEP","name":"Statement - Pass \u003d new com.kms.katalon.core.testobject.TestObject(Pass)","description":"Creamos un nuevo TestObject para el campo password\\r\\n","startTime":1509007277693,"endTime":1509007277694,"childRecords":[],"interuppted":false},{"index":35,"isIgnoredIfFailed":false,"type":"TEST_STEP","name":"Statement - Pass.addProperty(\"xpath\", EQUALS, \"//input[@id\u003d\u0027userPasswordField\u0027]\", true)","description":"Decimos que este testobject contiene la propiedad Xpath que nos interesa","startTime":1509007277695,"endTime":1509007277699,"childRecords":[],"interuppted":false},{"index":36,"isIgnoredIfFailed":false,"type":"TEST_STEP","name":"setText","message":"Text \u0027pass1\u0027 is set on object \u0027Pass\u0027","description":"rellenamos  el test Obect\\r\\n","startTime":1509007277700,"endTime":1509007278592,"childRecords":[{"testStatus":{"stackTrace":"","statusValue":"PASSED"},"type":"MESSAGE","name":"","message":"Text \u0027pass1\u0027 is set on object \u0027Pass\u0027","startTime":1509007278590,"endTime":0,"childRecords":[],"interuppted":false}],"interuppted":false},{"index":37,"isIgnoredIfFailed":false,"type":"TEST_STEP","name":"Statement - CPass \u003d new com.kms.katalon.core.testobject.TestObject(CPass)","description":"Creamos un nuevo TestObject para el campo Confirma Password\\r\\n","startTime":1509007278592,"endTime":1509007278593,"childRecords":[],"interuppted":false},{"index":38,"isIgnoredIfFailed":false,"type":"TEST_STEP","name":"Statement - CPass.addProperty(\"xpath\", EQUALS, \"//input[@id\u003d\u0027userRetypePasswordField\u0027]\", true)","description":"Decimos que este testobject contiene la propiedad Xpath que nos interesa","startTime":1509007278593,"endTime":1509007278593,"childRecords":[],"interuppted":false},{"index":39,"isIgnoredIfFailed":false,"type":"TEST_STEP","name":"setText","message":"Text \u0027pass1\u0027 is set on object \u0027CPass\u0027","description":"rellenamos  el test Obect\\r\\n","startTime":1509007278593,"endTime":1509007279375,"childRecords":[{"testStatus":{"stackTrace":"","statusValue":"PASSED"},"type":"MESSAGE","name":"","message":"Text \u0027pass1\u0027 is set on object \u0027CPass\u0027","startTime":1509007279371,"endTime":0,"childRecords":[],"interuppted":false}],"interuppted":false},{"index":40,"isIgnoredIfFailed":false,"type":"TEST_STEP","name":"Statement - Phone \u003d new com.kms.katalon.core.testobject.TestObject(Phone)","description":"Creamos un nuevo TestObject para el campo Phone\\r\\n","startTime":1509007279376,"endTime":1509007279382,"childRecords":[],"interuppted":false},{"index":41,"isIgnoredIfFailed":false,"type":"TEST_STEP","name":"Statement - Phone.addProperty(\"xpath\", EQUALS, \"//input[@id\u003d\u0027userPhoneField\u0027]\", true)","description":"Decimos que este testobject contiene la propiedad Xpath que nos interesa","startTime":1509007279383,"endTime":1509007279384,"childRecords":[],"interuppted":false},{"index":42,"isIgnoredIfFailed":false,"type":"TEST_STEP","name":"setText","message":"Text \u0027938050404\u0027 is set on object \u0027Phone\u0027","description":"rellenamos  el test Obect\\r\\n","startTime":1509007279384,"endTime":1509007280142,"childRecords":[{"testStatus":{"stackTrace":"","statusValue":"PASSED"},"type":"MESSAGE","name":"","message":"Text \u0027938050404\u0027 is set on object \u0027Phone\u0027","startTime":1509007280140,"endTime":0,"childRecords":[],"interuppted":false}],"interuppted":false},{"index":43,"isIgnoredIfFailed":false,"type":"TEST_STEP","name":"Statement - TermsOfUse \u003d new com.kms.katalon.core.testobject.TestObject(TermsOfUse)","description":"Creamos un nuevo TestObject para el checkbox de Politicas y terminos de Uso\\r\\n","startTime":1509007280143,"endTime":1509007280143,"childRecords":[],"interuppted":false},{"index":44,"isIgnoredIfFailed":false,"type":"TEST_STEP","name":"Statement - TermsOfUse.addProperty(\"xpath\", EQUALS, \"//input[@type\u003d\u0027checkbox\u0027][@class\u003d\u0027validate-required-check\u0027][ancestor::form[@id\u003d\u0027userForm\u0027]]\", true)","description":"Decimos que este testobject contiene la propiedad Xpath que nos interesa","startTime":1509007280145,"endTime":1509007280147,"childRecords":[],"interuppted":false},{"index":45,"isIgnoredIfFailed":false,"type":"TEST_STEP","name":"check","message":"Object \u0027TermsOfUse\u0027 is checked","description":"checkeamos  el test Obect\\r\\n","startTime":1509007280147,"endTime":1509007280998,"childRecords":[{"testStatus":{"stackTrace":"","statusValue":"PASSED"},"type":"MESSAGE","name":"","message":"Object \u0027TermsOfUse\u0027 is checked","startTime":1509007280986,"endTime":0,"childRecords":[],"interuppted":false}],"interuppted":false},{"index":46,"isIgnoredIfFailed":false,"type":"TEST_STEP","name":"Statement - Country1 \u003d new com.kms.katalon.core.testobject.TestObject(Country1)","description":"Creamos un nuevo TestObject para el input 1 de Country\\r\\n","startTime":1509007281002,"endTime":1509007281005,"childRecords":[],"interuppted":false},{"index":47,"isIgnoredIfFailed":false,"type":"TEST_STEP","name":"Statement - Country1.addProperty(\"xpath\", EQUALS, \"//select[@id\u003d\u0027userCountryField\u0027]\", true)","description":"Decimos que este testobject contiene la propiedad Xpath que nos interesa","startTime":1509007281005,"endTime":1509007281007,"childRecords":[],"interuppted":false},{"index":48,"isIgnoredIfFailed":false,"type":"TEST_STEP","name":"selectOptionByLabel","message":"All options with label \u0027hong kong\u0027 are selected in object \u0027Country1\u0027 ","description":"Seleccionamos la opcion por valor  el test Obect\\r\\n","startTime":1509007281007,"endTime":1509007281686,"childRecords":[{"testStatus":{"stackTrace":"","statusValue":"PASSED"},"type":"MESSAGE","name":"","message":"All options with label \u0027hong kong\u0027 are selected in object \u0027Country1\u0027 ","startTime":1509007281685,"endTime":0,"childRecords":[],"interuppted":false}],"interuppted":false},{"index":49,"isIgnoredIfFailed":false,"type":"TEST_STEP","name":"Statement - Country2 \u003d new com.kms.katalon.core.testobject.TestObject(Country2)","description":"Creamos un nuevo TestObject para el input 2 de Country\\r\\n","startTime":1509007281687,"endTime":1509007281688,"childRecords":[],"interuppted":false},{"index":50,"isIgnoredIfFailed":false,"type":"TEST_STEP","name":"Statement - Country2.addProperty(\"xpath\", EQUALS, \"//div[contains(@class, \u0027countriesSelector\u0027)]/select\", true)","description":"Decimos que este testobject contiene la propiedad Xpath que nos interesa","startTime":1509007281688,"endTime":1509007281688,"childRecords":[],"interuppted":false},{"index":51,"isIgnoredIfFailed":false,"type":"TEST_STEP","name":"selectOptionByLabel","message":"All options with label \u0027hong kong island\u0027 are selected in object \u0027Country2\u0027 ","description":"Seleccionamos la opcion por valor  el test Obect\\r\\n","startTime":1509007281688,"endTime":1509007282895,"childRecords":[{"testStatus":{"stackTrace":"","statusValue":"PASSED"},"type":"MESSAGE","name":"","message":"All options with label \u0027hong kong island\u0027 are selected in object \u0027Country2\u0027 ","startTime":1509007282892,"endTime":0,"childRecords":[],"interuppted":false}],"interuppted":false},{"index":52,"isIgnoredIfFailed":false,"type":"TEST_STEP","name":"Statement - TercerArea \u003d new com.kms.katalon.core.testobject.TestObject(TercerArea)","description":"Creamos un nuevo TestObject\\r\\n","startTime":1509007282896,"endTime":1509007282897,"childRecords":[],"interuppted":false},{"index":53,"isIgnoredIfFailed":false,"type":"TEST_STEP","name":"Statement - TercerArea.addProperty(\"xpath\", EQUALS, \"//div[contains(@class, \u0027countriesSelector\u0027)]/div/select\", true)","description":"Decimos que este tebobject contiene la propiedad Xpath que nos interesa","startTime":1509007282897,"endTime":1509007282898,"childRecords":[],"interuppted":false},{"index":54,"isIgnoredIfFailed":false,"type":"TEST_STEP","name":"selectOptionByLabel","message":"All options with label \u0027central and western\u0027 are selected in object \u0027TercerArea\u0027 ","description":"Seleccionamos el valor deseado\\r\\n","startTime":1509007282899,"endTime":1509007285003,"childRecords":[{"testStatus":{"stackTrace":"","statusValue":"PASSED"},"type":"MESSAGE","name":"","message":"All options with label \u0027central and western\u0027 are selected in object \u0027TercerArea\u0027 ","startTime":1509007284998,"endTime":0,"childRecords":[],"interuppted":false}],"interuppted":false},{"index":55,"isIgnoredIfFailed":false,"type":"TEST_STEP","name":"Statement - CuartaArea \u003d new com.kms.katalon.core.testobject.TestObject(CuartaArea)","description":"Se repite Hasta...","startTime":1509007285003,"endTime":1509007285003,"childRecords":[],"interuppted":false},{"index":56,"isIgnoredIfFailed":false,"type":"TEST_STEP","name":"Statement - CuartaArea.addProperty(\"xpath\", EQUALS, \"//div[contains(@class, \u0027countriesSelector\u0027)]/div/div/select\", true)","description":"","startTime":1509007285003,"endTime":1509007285011,"childRecords":[],"interuppted":false},{"index":57,"isIgnoredIfFailed":false,"type":"TEST_STEP","name":"selectOptionByLabel","message":"All options with label \u0027central\u0027 are selected in object \u0027CuartaArea\u0027 ","description":"","startTime":1509007285013,"endTime":1509007287118,"childRecords":[{"testStatus":{"stackTrace":"","statusValue":"PASSED"},"type":"MESSAGE","name":"","message":"All options with label \u0027central\u0027 are selected in object \u0027CuartaArea\u0027 ","startTime":1509007287116,"endTime":0,"childRecords":[],"interuppted":false}],"interuppted":false},{"index":58,"isIgnoredIfFailed":false,"type":"TEST_STEP","name":"Statement - QuintaArea \u003d new com.kms.katalon.core.testobject.TestObject(QuintaArea)","description":"","startTime":1509007287118,"endTime":1509007287119,"childRecords":[],"interuppted":false},{"index":59,"isIgnoredIfFailed":false,"type":"TEST_STEP","name":"Statement - QuintaArea.addProperty(\"xpath\", EQUALS, \"//div[contains(@class, \u0027countriesSelector\u0027)]/div/div/div/select\", true)","description":"","startTime":1509007287120,"endTime":1509007287121,"childRecords":[],"interuppted":false},{"index":60,"isIgnoredIfFailed":false,"type":"TEST_STEP","name":"selectOptionByLabel","message":"All options with label \u0027admiralty\u0027 are selected in object \u0027QuintaArea\u0027 ","description":"Aqui!","startTime":1509007287122,"endTime":1509007289282,"childRecords":[{"testStatus":{"stackTrace":"","statusValue":"PASSED"},"type":"MESSAGE","name":"","message":"All options with label \u0027admiralty\u0027 are selected in object \u0027QuintaArea\u0027 ","startTime":1509007289279,"endTime":0,"childRecords":[],"interuppted":false}],"interuppted":false},{"index":61,"isIgnoredIfFailed":false,"type":"TEST_STEP","name":"Statement - Acabar \u003d new com.kms.katalon.core.testobject.TestObject(Acabar)","description":"Creamos un nuevo TestObject para el boton de acabado\\r\\n","startTime":1509007289282,"endTime":1509007289284,"childRecords":[],"interuppted":false},{"index":62,"isIgnoredIfFailed":false,"type":"TEST_STEP","name":"Statement - Acabar.addProperty(\"xpath\", EQUALS, \"//input[@id\u003d\u0027saveUserButton\u0027]\", true)","description":"Decimos que este testobject contiene la propiedad Xpath que nos interesa","startTime":1509007289284,"endTime":1509007289284,"childRecords":[],"interuppted":false},{"index":63,"isIgnoredIfFailed":false,"type":"TEST_STEP","name":"click","message":"Object: \u0027Acabar\u0027 is clicked on","description":"clickamos en el test Obect\\r\\n","startTime":1509007289284,"endTime":1509007290359,"childRecords":[{"testStatus":{"stackTrace":"","statusValue":"PASSED"},"type":"MESSAGE","name":"","message":"Object: \u0027Acabar\u0027 is clicked on","startTime":1509007290358,"endTime":0,"childRecords":[],"interuppted":false}],"interuppted":false},{"index":64,"isIgnoredIfFailed":false,"type":"TEST_STEP","name":"closeBrowser","message":"Browser is closed","description":"","startTime":1509007290361,"endTime":1509007291947,"childRecords":[{"testStatus":{"stackTrace":"","statusValue":"PASSED"},"type":"MESSAGE","name":"","message":"Browser is closed","startTime":1509007291943,"endTime":0,"childRecords":[],"interuppted":false}],"interuppted":false},{"testStatus":{"stackTrace":"","statusValue":"PASSED"},"type":"MESSAGE","name":"","message":"Test Cases/Crear User","startTime":1509007291947,"endTime":0,"childRecords":[],"interuppted":false}],"interuppted":false}],"interuppted":false}